[{
  "party_member_names": [
    "サーナイト",
    "スイクン",
    "スピアー",
    "ナットレイ",
    "バンギラス",
    "霊獣ランドロス"
  ],
  "party_member_infos": [
    {
      "name": "サーナイト",
      "item": "サーナイトナイト",
      "move": [
        "ちょうはつ",
        "ハイパーボイス",
        "こごえるかぜ",
        "サイコキネシス"
      ]
    },
    {
      "name": "スイクン",
      "item": "カゴのみ",
      "move": [
        "ほえる",
        "ねむる",
        "めいそう",
        "ねっとう"
      ]
    },
    {
      "name": "スピアー",
      "item": "スピアーナイト",
      "move": [
        "まもる",
        "はたきおとす",
        "どくづき",
        "とんぼがえり"
      ]
    },
    {
      "name": "ナットレイ",
      "item": "たべのこし",
      "move": [
        "でんじは",
        "アイアンヘッド",
        "ステルスロック",
        "パワーウィップ"
      ]
    },
    {
      "name": "バンギラス",
      "item": "とつげきチョッキ",
      "move": [
        "からげんき",
        "がんせきふうじ",
        "しっぺがえし",
        "あくのはどう"
      ]
    },
    {
      "name": "霊獣ランドロス",
      "item": "こだわりスカーフ",
      "move": [
        "とんぼがえり",
        "はたきおとす",
        "いわなだれ",
        "じしん"
      ]
    }
  ]
},
{
  "party_member_names": [
    "ウォッシュロトム",
    "バシャーモ",
    "ガルーラ",
    "ニンフィア",
    "クレセリア",
    "リザードン"
  ],
  "party_member_infos": [
    {
      "name": "ウォッシュロトム",
      "item": "ひかりのねんど",
      "move": [
        "リフレクター",
        "ひかりのかべ",
        "おにび",
        "ボルトチェンジ"
      ]
    },
    {
      "name": "バシャーモ",
      "item": "じゃくてんほけん",
      "move": [
        "ビルドアップ",
        "バトンタッチ",
        "みがわり",
        "まもる"
      ]
    },
    {
      "name": "ガルーラ",
      "item": "ガルーラナイト",
      "move": [
        "おんがえし",
        "いわなだれ",
        "じしん",
        "みがわり"
      ]
    },
    {
      "name": "ニンフィア",
      "item": "こだわりメガネ",
      "move": [
        "ハイパーボイス",
        "めざめるパワー地",
        "シャドーボール",
        "はかいこうせん"
      ]
    },
    {
      "name": "クレセリア",
      "item": "ゴツゴツメット",
      "move": [
        "ムーンフォース",
        "でんじは",
        "つきのひかり",
        "みかづきのまい"
      ]
    },
    {
      "name": "リザードン",
      "item": "リザードナイトY",
      "move": [
        "かえんほうしゃ",
        "オーバーヒート",
        "ソーラービーム",
        "じしん"
      ]
    }
  ]
},
{
  "party_member_names": [
    "カバルドン",
    "ガブリアス",
    "ヒードラン",
    "サンダー",
    "ハッサム",
    "ヘラクロス"
  ],
  "party_member_infos": [
    {
      "name": "カバルドン",
      "item": "ゴツゴツメット",
      "move": [
        "じしん",
        "ステルスロック",
        "ほえる",
        "なまける"
      ]
    },
    {
      "name": "ガブリアス",
      "item": "きあいのタスキ",
      "move": [
        "げきりん",
        "じしん",
        "だいもんじ",
        "がんせきふうじ"
      ]
    },
    {
      "name": "ヒードラン",
      "item": "たべのこし",
      "move": [
        "ふんえん",
        "めざめるパワー氷",
        "どくどく",
        "みがわり"
      ]
    },
    {
      "name": "サンダー",
      "item": "こだわりスカーフ",
      "move": [
        "１０まんボルト",
        "ボルトチェンジ",
        "ねっぷう",
        "めざめるパワー氷"
      ]
    },
    {
      "name": "ハッサム",
      "item": "いのちのたま",
      "move": [
        "バレットパンチ",
        "むしくい",
        "でんこうせっか",
        "つるぎのまい"
      ]
    },
    {
      "name": "ヘラクロス",
      "item": "ヘラクロスナイト",
      "move": [
        "インファイト",
        "ミサイルばり",
        "タネマシンガン",
        "じしん"
      ]
    }
  ]
},
{
  "party_member_names": [
    "クレッフィ",
    "メタモン",
    "スターミー",
    "トゲキッス",
    "バンギラス",
    "ガブリアス"
  ],
  "party_member_infos": [
    {
      "name": "クレッフィ",
      "item": "たべのこし",
      "move": [
        "でんじは",
        "いばる",
        "みがわり",
        "イカサマ"
      ]
    },
    {
      "name": "メタモン",
      "item": "きあいのタスキ",
      "move": [
        "へんしん",
        "",
        "",
        ""
      ]
    },
    {
      "name": "スターミー",
      "item": "ひかりのこな",
      "move": [
        "ねっとう",
        "ちいさくなる",
        "じこさいせい",
        "みがわり"
      ]
    },
    {
      "name": "トゲキッス",
      "item": "こだわりスカーフ",
      "move": [
        "エアスラッシュ",
        "マジカルシャイン",
        "かえんほうしゃ",
        "はどうだん"
      ]
    },
    {
      "name": "バンギラス",
      "item": "こだわりメガネ",
      "move": [
        "あくのはどう",
        "１０まんボルト",
        "れいとうビーム",
        "だいもんじ"
      ]
    },
    {
      "name": "ガブリアス",
      "item": "ガブリアスナイト",
      "move": [
        "げきりん",
        "じしん",
        "みがわり",
        "つるぎのまい"
      ]
    }
  ]
},
{
  "party_member_names": [
    "ラグラージ",
    "カイリュー",
    "ハッサム",
    "ガルーラ",
    "化身ボルトロス",
    "ゲンガー"
  ],
  "party_member_infos": [
    {
      "name": "ラグラージ",
      "item": "ゴツゴツメット",
      "move": [
        "なみのり",
        "れいとうビーム",
        "だいちのちから",
        "どくどく"
      ]
    },
    {
      "name": "カイリュー",
      "item": "じゃくてんほけん",
      "move": [
        "りゅうのはどう",
        "かえんほうしゃ",
        "１０まんボルト",
        "しんそく"
      ]
    },
    {
      "name": "ハッサム",
      "item": "ハッサムナイト",
      "move": [
        "バレットパンチ",
        "はたきおとす",
        "ばかぢから",
        "つるぎのまい"
      ]
    },
    {
      "name": "ガルーラ",
      "item": "ガルーラナイト",
      "move": [
        "ちきゅうなげ",
        "れいとうビーム",
        "シャドーボール",
        "みがわり"
      ]
    },
    {
      "name": "化身ボルトロス",
      "item": "きあいのタスキ",
      "move": [
        "１０まんボルト",
        "めざめるパワー氷",
        "でんじは",
        "いばる"
      ]
    },
    {
      "name": "ゲンガー",
      "item": "いのちのたま",
      "move": [
        "たたりめ",
        "ヘドロばくだん",
        "きあいだま",
        "おにび"
      ]
    }
  ]
},
{
  "party_member_names": [
    "ガブリアス",
    "ガルーラ",
    "クレセリア",
    "ヒードラン",
    "マリルリ",
    "フシギバナ"
  ],
  "party_member_infos": [
    {
      "name": "ガブリアス",
      "item": "こだわりスカーフ",
      "move": [
        "げきりん",
        "じしん",
        "ストーンエッジ",
        "ほのおのキバ"
      ]
    },
    {
      "name": "ガルーラ",
      "item": "ガルーラナイト",
      "move": [
        "ちきゅうなげ",
        "シャドーボール",
        "みがわり",
        "れいとうビーム"
      ]
    },
    {
      "name": "クレセリア",
      "item": "ゴツゴツメット",
      "move": [
        "サイコキネシス",
        "めざめるパワー炎",
        "どくどく",
        "みかづきのまい"
      ]
    },
    {
      "name": "ヒードラン",
      "item": "こだわりメガネ",
      "move": [
        "かえんほうしゃ",
        "ラスターカノン",
        "あくのはどう",
        "ねごと"
      ]
    },
    {
      "name": "マリルリ",
      "item": "とつげきチョッキ",
      "move": [
        "たきのぼり",
        "じゃれつく",
        "はたきおとす",
        "アクアジェット"
      ]
    },
    {
      "name": "フシギバナ",
      "item": "フシギバナイト",
      "move": [
        "ヘドロばくだん",
        "じしん",
        "ねむりごな",
        "ギガドレイン"
      ]
    }
  ]
},
{
  "party_member_names": [
    "バンギラス",
    "ドリュウズ",
    "エルフーン",
    "ゲンガー",
    "霊獣ボルトロス",
    "スイクン"
  ],
  "party_member_infos": [
    {
      "name": "バンギラス",
      "item": "バンギラスナイト",
      "move": [
        "ストーンエッジ",
        "じしん",
        "れいとうパンチ",
        "りゅうのまい"
      ]
    },
    {
      "name": "ドリュウズ",
      "item": "いのちのたま",
      "move": [
        "じしん",
        "いわなだれ",
        "アイアンヘッド",
        "つるぎのまい"
      ]
    },
    {
      "name": "エルフーン",
      "item": "だっしゅつボタン",
      "move": [
        "ムーンフォース",
        "エナジーボール",
        "おいかぜ",
        "アンコール"
      ]
    },
    {
      "name": "ゲンガー",
      "item": "ゲンガナイト",
      "move": [
        "シャドーボール",
        "ほろびのうた",
        "まもる",
        "みちづれ"
      ]
    },
    {
      "name": "霊獣ボルトロス",
      "item": "こだわりメガネ",
      "move": [
        "１０まんボルト",
        "めざめるパワー飛",
        "きあいだま",
        "ボルトチェンジ"
      ]
    },
    {
      "name": "スイクン",
      "item": "ゴツゴツメット",
      "move": [
        "なみのり",
        "れいとうビーム",
        "ぜったいれいど",
        "おいかぜ"
      ]
    }
  ]
},
{
  "party_member_names": [
    "リザードン",
    "クレセリア",
    "ガブリアス",
    "化身ボルトロス",
    "ガルーラ",
    "マリルリ"
  ],
  "party_member_infos": [
    {
      "name": "リザードン",
      "item": "リザードナイトX",
      "move": [
        "げきりん",
        "フレアドライブ",
        "みがわり",
        "りゅうのまい"
      ]
    },
    {
      "name": "クレセリア",
      "item": "ひかりのねんど",
      "move": [
        "サイコキネシス",
        "みかづきのまい",
        "リフレクター",
        "ひかりのかべ"
      ]
    },
    {
      "name": "ガブリアス",
      "item": "こだわりハチマキ",
      "move": [
        "げきりん",
        "じしん",
        "ストーンエッジ",
        "どくづき"
      ]
    },
    {
      "name": "化身ボルトロス",
      "item": "いのちのたま",
      "move": [
        "１０まんボルト",
        "めざめるパワー飛",
        "くさむすび",
        "でんじは"
      ]
    },
    {
      "name": "ガルーラ",
      "item": "ガルーラナイト",
      "move": [
        "すてみタックル",
        "じしん",
        "いわなだれ",
        "ふいうち"
      ]
    },
    {
      "name": "マリルリ",
      "item": "オボンのみ",
      "move": [
        "じゃれつく",
        "たきのぼり",
        "アクアジェット",
        "はらだいこ"
      ]
    }
  ]
},
{
  "party_member_names": [
    "ゲッコウガ",
    "エルレイド",
    "クレセリア",
    "エンテイ",
    "霊獣ランドロス",
    "ボーマンダ"
  ],
  "party_member_infos": [
    {
      "name": "ゲッコウガ",
      "item": "いのちのたま",
      "move": [
        "れいとうビーム",
        "くさむすび",
        "けたぐり",
        "ダストシュート"
      ]
    },
    {
      "name": "エルレイド",
      "item": "エルレイドナイト",
      "move": [
        "ドレインパンチ",
        "はたきおとす",
        "つるぎのまい",
        "みがわり"
      ]
    },
    {
      "name": "クレセリア",
      "item": "ゴツゴツメット",
      "move": [
        "ひかりのかべ",
        "みかづきのまい",
        "れいとうビーム",
        "どくどく"
      ]
    },
    {
      "name": "エンテイ",
      "item": "こだわりハチマキ",
      "move": [
        "せいなるほのお",
        "じならし",
        "ストーンエッジ",
        "アイアンヘッド"
      ]
    },
    {
      "name": "霊獣ランドロス",
      "item": "こだわりスカーフ",
      "move": [
        "じしん",
        "ストーンエッジ",
        "とんぼがえり",
        "だいばくはつ"
      ]
    },
    {
      "name": "ボーマンダ",
      "item": "ボーマンダナイト",
      "move": [
        "すてみタックル",
        "からげんき",
        "りゅうせいぐん",
        "かえんほうしゃ"
      ]
    }
  ]
},
{
  "party_member_names": [
    "ファイアロー",
    "ゲンガー",
    "マンムー",
    "ナットレイ",
    "ガブリアス",
    "ヒードラン"
  ],
  "party_member_infos": [
    {
      "name": "ファイアロー",
      "item": "ゴツゴツメット",
      "move": [
        "ブレイブバード",
        "おにび",
        "ちょうはつ",
        "はねやすめ"
      ]
    },
    {
      "name": "ゲンガー",
      "item": "ゲンガナイト",
      "move": [
        "シャドーボール",
        "きあいだま",
        "まもる",
        "みちづれ"
      ]
    },
    {
      "name": "マンムー",
      "item": "とつげきチョッキ",
      "move": [
        "じしん",
        "つららばり",
        "ストーンエッジ",
        "こおりのつぶて"
      ]
    },
    {
      "name": "ナットレイ",
      "item": "たべのこし",
      "move": [
        "パワーウィップ",
        "ジャイロボール",
        "まもる",
        "やどりぎのタネ"
      ]
    },
    {
      "name": "ガブリアス",
      "item": "こだわりハチマキ",
      "move": [
        "げきりん",
        "じしん",
        "どくづき",
        "ダブルチョップ"
      ]
    },
    {
      "name": "ヒードラン",
      "item": "ふうせん",
      "move": [
        "マグマストーム",
        "だいちのちから",
        "ステルスロック",
        "ほえる"
      ]
    }
  ]
},
{
  "party_member_names": [
    "ゲンガー",
    "マリルリ",
    "サンダー",
    "ナットレイ",
    "マンムー",
    "ウルガモス"
  ],
  "party_member_infos": [
    {
      "name": "ゲンガー",
      "item": "ゲンガナイト",
      "move": [
        "シャドーボール",
        "きあいだま",
        "こごえるかぜ",
        "みちづれ"
      ]
    },
    {
      "name": "マリルリ",
      "item": "オボンのみ",
      "move": [
        "たきのぼり",
        "じゃれつく",
        "アクアジェット",
        "はらだいこ"
      ]
    },
    {
      "name": "サンダー",
      "item": "ゴツゴツメット",
      "move": [
        "１０まんボルト",
        "めざめるパワー氷",
        "どくどく",
        "はねやすめ"
      ]
    },
    {
      "name": "ナットレイ",
      "item": "たべのこし",
      "move": [
        "ジャイロボール",
        "タネマシンガン",
        "やどりぎのタネ",
        "まもる"
      ]
    },
    {
      "name": "ウルガモス",
      "item": "ラムのみ",
      "move": [
        "だいもんじ",
        "むしのさざめき",
        "ちょうのまい",
        "みがわり"
      ]
    },
    {
      "name": "マンムー",
      "item": "きあいのタスキ",
      "move": [
        "じしん",
        "こおりのつぶて",
        "フリーズドライ",
        "ステルスロック"
      ]
    }
  ]
},
{
  "party_member_names": [
    "フシギバナ",
    "カイリュー",
    "クレセリア",
    "ヒードラン",
    "化身ボルトロス",
    "ローブシン"
  ],
  "party_member_infos": [
    {
      "name": "フシギバナ",
      "item": "フシギバナイト",
      "move": [
        "ギガドレイン",
        "ヘドロばくだん",
        "めざめるパワー炎",
        "ほえる"
      ]
    },
    {
      "name": "カイリュー",
      "item": "こだわりハチマキ",
      "move": [
        "げきりん",
        "しんそく",
        "じしん",
        "アイアンヘッド"
      ]
    },
    {
      "name": "クレセリア",
      "item": "ゴツゴツメット",
      "move": [
        "サイコキネシス",
        "れいとうビーム",
        "どくどく",
        "つきのひかり"
      ]
    },
    {
      "name": "ヒードラン",
      "item": "こだわりメガネ",
      "move": [
        "オーバーヒート",
        "ラスターカノン",
        "あくのはどう",
        "りゅうのはどう"
      ]
    },
    {
      "name": "化身ボルトロス",
      "item": "いのちのたま",
      "move": [
        "１０まんボルト",
        "めざめるパワー飛",
        "きあいだま",
        "ちょうはつ"
      ]
    },
    {
      "name": "ローブシン",
      "item": "とつげきチョッキ",
      "move": [
        "ドレインパンチ",
        "マッハパンチ",
        "れいとうパンチ",
        "はたきおとす"
      ]
    }
  ]
},
{
  "party_member_names": [
    "化身ボルトロス",
    "ガブリアス",
    "クチート",
    "ヤミラミ",
    "キノガッサ",
    "スイクン"
  ],
  "party_member_infos": [
    {
      "name": "化身ボルトロス",
      "item": "オボンのみ",
      "move": [
        "ボルトチェンジ",
        "めざめるパワー氷",
        "でんじは",
        "ちょうはつ"
      ]
    },
    {
      "name": "ガブリアス",
      "item": "いのちのたま",
      "move": [
        "げきりん",
        "じしん",
        "ストーンエッジ",
        "つるぎのまい"
      ]
    },
    {
      "name": "クチート",
      "item": "クチートナイト",
      "move": [
        "じゃれつく",
        "はたきおとす",
        "ふいうち",
        "つるぎのまい"
      ]
    },
    {
      "name": "ヤミラミ",
      "item": "ヤミラミナイト",
      "move": [
        "バークアウト",
        "めいそう",
        "おにび",
        "じこさいせい"
      ]
    },
    {
      "name": "キノガッサ",
      "item": "きあいのタスキ",
      "move": [
        "タネマシンガン",
        "マッハパンチ",
        "がんせきふうじ",
        "はっけい"
      ]
    },
    {
      "name": "スイクン",
      "item": "ゴツゴツメット",
      "move": [
        "ねっとう",
        "れいとうビーム",
        "リフレクター",
        "ミラーコート"
      ]
    }
  ]
},
{
  "party_member_names": [
    "エムリット",
    "クレッフィ",
    "バンギラス",
    "トリトドン",
    "ウルガモス",
    "ボーマンダ"
  ],
  "party_member_infos": [
    {
      "name": "エムリット",
      "item": "こだわりスカーフ",
      "move": [
        "サイコキネシス",
        "れいとうビーム",
        "トリック",
        "とんぼがえり"
      ]
    },
    {
      "name": "クレッフィ",
      "item": "たべのこし",
      "move": [
        "いばる",
        "みがわり",
        "でんじは",
        "イカサマ"
      ]
    },
    {
      "name": "バンギラス",
      "item": "バンギラスナイト",
      "move": [
        "かみくだく",
        "ストーンエッジ",
        "みがわり",
        "りゅうのまい"
      ]
    },
    {
      "name": "トリトドン",
      "item": "オボンのみ",
      "move": [
        "だいちのちから",
        "ねっとう",
        "れいとうビーム",
        "じわれ"
      ]
    },
    {
      "name": "ウルガモス",
      "item": "ラムのみ",
      "move": [
        "だいもんじ",
        "ギガドレイン",
        "ちょうのまい",
        "めざめるパワー氷"
      ]
    },
    {
      "name": "ボーマンダ",
      "item": "ボーマンダナイト",
      "move": [
        "すてみタックル",
        "じしん",
        "ハイパーボイス",
        "りゅうせいぐん"
      ]
    }
  ]
},
{
  "party_member_names": [
    "ドンファン",
    "メタグロス",
    "カイロス",
    "バシャーモ",
    "マリルリ",
    "オニゴーリ"
  ],
  "party_member_infos": [
    {
      "name": "ドンファン",
      "item": "ラムのみ",
      "move": [
        "タネばくだん",
        "ステルスロック",
        "こおりのつぶて",
        "がむしゃら"
      ]
    },
    {
      "name": "メタグロス",
      "item": "ぼうじんゴーグル",
      "move": [
        "コメットパンチ",
        "バレットパンチ",
        "だいばくはつ",
        "ステルスロック"
      ]
    },
    {
      "name": "カイロス",
      "item": "カイロスナイト",
      "move": [
        "おんがえし",
        "じしん",
        "でんこうせっか",
        "つるぎのまい"
      ]
    },
    {
      "name": "バシャーモ",
      "item": "いのちのたま",
      "move": [
        "かえんほうしゃ",
        "ばかぢから",
        "かみなりパンチ",
        "はたきおとす"
      ]
    },
    {
      "name": "マリルリ",
      "item": "オボンのみ",
      "move": [
        "たきのぼり",
        "アクアジェット",
        "じゃれつく",
        "はらだいこ"
      ]
    },
    {
      "name": "オニゴーリ",
      "item": "オニゴーリナイト",
      "move": [
        "おんがえし",
        "こおりのつぶて",
        "じしん",
        "だいばくはつ"
      ]
    }
  ]
},
{
  "party_member_names": [
    "ライボルト",
    "霊獣ランドロス",
    "クレセリア",
    "ヒードラン",
    "キノガッサ",
    "ゲンガー"
  ],
  "party_member_infos": [
    {
      "name": "ライボルト",
      "item": "ライボルトナイト",
      "move": [
        "めざめるパワー氷",
        "１０まんボルト",
        "かえんほうしゃ",
        "ボルトチェンジ"
      ]
    },
    {
      "name": "霊獣ランドロス",
      "item": "こだわりスカーフ",
      "move": [
        "じしん",
        "とんぼがえり",
        "いわなだれ",
        "ばかぢから"
      ]
    },
    {
      "name": "クレセリア",
      "item": "ゴツゴツメット",
      "move": [
        "サイコキネシス",
        "れいとうビーム",
        "つきのひかり",
        "でんじは"
      ]
    },
    {
      "name": "ヒードラン",
      "item": "たべのこし",
      "move": [
        "マグマストーム",
        "だいちのちから",
        "どくどく",
        "まもる"
      ]
    },
    {
      "name": "キノガッサ",
      "item": "どくどくだま",
      "move": [
        "キノコのほうし",
        "みがわり",
        "タネマシンガン",
        "ビルドアップ"
      ]
    },
    {
      "name": "ゲンガー",
      "item": "ゲンガナイト",
      "move": [
        "たたりめ",
        "おにび",
        "ちょうはつ",
        "みちづれ"
      ]
    }
  ]
},
{
  "party_member_names": [
    "ボーマンダ",
    "ローブシン",
    "クレセリア",
    "ヒードラン",
    "ニンフィア",
    "サンダー"
  ],
  "party_member_infos": [
    {
      "name": "ボーマンダ",
      "item": "ボーマンダナイト",
      "move": [
        "ドラゴンダイブ",
        "すてみタックル",
        "からげんき",
        "じしん"
      ]
    },
    {
      "name": "ローブシン",
      "item": "とつげきチョッキ",
      "move": [
        "ドレインパンチ",
        "いわなだれ",
        "はたきおとす",
        "マッハパンチ"
      ]
    },
    {
      "name": "クレセリア",
      "item": "ゴツゴツメット",
      "move": [
        "サイコキネシス",
        "れいとうビーム",
        "どくどく",
        "つきのひかり"
      ]
    },
    {
      "name": "ヒードラン",
      "item": "たべのこし",
      "move": [
        "マグマストーム",
        "だいちのちから",
        "どくどく",
        "ステルスロック"
      ]
    },
    {
      "name": "ニンフィア",
      "item": "カゴのみ",
      "move": [
        "ハイパーボイス",
        "でんこうせっか",
        "めいそう",
        "ねむる"
      ]
    },
    {
      "name": "サンダー",
      "item": "オボンのみ",
      "move": [
        "１０まんボルト",
        "めざめるパワー氷",
        "でんじは",
        "はねやすみ"
      ]
    }
  ]
},
{
  "party_member_names": [
    "ボーマンダ",
    "クレッフィ",
    "リザードン",
    "キノガッサ",
    "サンダー",
    "ポリゴン２"
  ],
  "party_member_infos": [
    {
      "name": "ボーマンダ",
      "item": "ボーマンダナイト",
      "move": [
        "りゅうせいぐん",
        "ハイパーボイス",
        "だいもんじ",
        "じしん"
      ]
    },
    {
      "name": "クレッフィ",
      "item": "たべのこし",
      "move": [
        "イカサマ",
        "どくどく",
        "いばる",
        "みがわり"
      ]
    },
    {
      "name": "リザードン",
      "item": "リザードナイトX",
      "move": [
        "ニトロチャージ",
        "ドラゴンクロー",
        "おにび",
        "はねやすめ"
      ]
    },
    {
      "name": "キノガッサ",
      "item": "きあいのタスキ",
      "move": [
        "タネマシンガン",
        "マッハパンチ",
        "がんせきふうじ",
        "キノコのほうし"
      ]
    },
    {
      "name": "サンダー",
      "item": "ゴツゴツメット",
      "move": [
        "ボルトチェンジ",
        "ねっぷう",
        "どくどく",
        "はねやすめ"
      ]
    },
    {
      "name": "ポリゴン２",
      "item": "しんかのきせき",
      "move": [
        "れいとうビーム",
        "ほうでん",
        "イカサマ",
        "じこさいせい"
      ]
    }
  ]
},
{
  "party_member_names": [
    "ユキノオー",
    "ガブリアス",
    "サンダー",
    "クレセリア",
    "ヒードラン",
    "トゲキッス"
  ],
  "party_member_infos": [
    {
      "name": "ユキノオー",
      "item": "ユキノオナイト",
      "move": [
        "ウッドハンマー",
        "ふぶき",
        "じしん",
        "こおりのつぶて"
      ]
    },
    {
      "name": "ガブリアス",
      "item": "こだわりハチマキ",
      "move": [
        "げきりん",
        "じしん",
        "ストーンエッジ",
        "ねごと"
      ]
    },
    {
      "name": "サンダー",
      "item": "ラムのみ",
      "move": [
        "ボルトチェンジ",
        "めざめるパワー氷",
        "でんじは",
        "はねやすめ"
      ]
    },
    {
      "name": "クレセリア",
      "item": "ゴツゴツメット",
      "move": [
        "れいとうビーム",
        "つきのひかり",
        "トリックルーム",
        "みかづきのまい"
      ]
    },
    {
      "name": "ヒードラン",
      "item": "たべのこし",
      "move": [
        "マグマストーム",
        "おにび",
        "まもる",
        "だいちのちから"
      ]
    },
    {
      "name": "トゲキッス",
      "item": "こだわりスカーフ",
      "move": [
        "エアスラッシュ",
        "マジカルシャイン",
        "トリック",
        "はどうだん"
      ]
    }
  ]
},
{
  "party_member_names": [
    "ガルーラ",
    "ガブリアス",
    "スイクン",
    "ウルガモス",
    "ボーマンダ",
    "ナットレイ"
  ],
  "party_member_infos": [
    {
      "name": "ガルーラ",
      "item": "ガルーラナイト",
      "move": [
        "すてみタックル",
        "けたぐり",
        "れいとうパンチ",
        "ねこだまし"
      ]
    },
    {
      "name": "ガブリアス",
      "item": "ヤチェのみ",
      "move": [
        "げきりん",
        "じしん",
        "がんせきふうじ",
        "つるぎのまい"
      ]
    },
    {
      "name": "スイクン",
      "item": "カゴのみ",
      "move": [
        "ハイドロポンプ",
        "れいとうビーム",
        "めいそう",
        "ねむる"
      ]
    },
    {
      "name": "ウルガモス",
      "item": "ラムのみ",
      "move": [
        "だいもんじ",
        "むしのさざめき",
        "めざめるパワー氷",
        "ちょうのまい"
      ]
    },
    {
      "name": "ボーマンダ",
      "item": "ボーマンダナイト",
      "move": [
        "すてみタックル",
        "からげんき",
        "じしん",
        "りゅうのまい"
      ]
    },
    {
      "name": "ナットレイ",
      "item": "きあいのタスキ",
      "move": [
        "はたきおとす",
        "だいばくはつ",
        "でんじは",
        "ステルスロック"
      ]
    }
  ]
},
{
  "party_member_names": [
    "カバルドン",
    "ラッキー",
    "ボーマンダ",
    "化身ボルトロス",
    "ピクシー",
    "ゲンガー"
  ],
  "party_member_infos": [
    {
      "name": "カバルドン",
      "item": "ゴツゴツメット",
      "move": [
        "じしん",
        "がんせきふうじ",
        "なまける",
        "いばる"
      ]
    },
    {
      "name": "ラッキー",
      "item": "しんかのきせき",
      "move": [
        "ちきゅうなげ",
        "タマゴうみ",
        "でんじは",
        "いばる"
      ]
    },
    {
      "name": "ボーマンダ",
      "item": "ボーマンダナイト",
      "move": [
        "すてみタックル",
        "からげんき",
        "ねむる",
        "いびき"
      ]
    },
    {
      "name": "化身ボルトロス",
      "item": "オボンのみ",
      "move": [
        "１０まんボルト",
        "めざめるパワー氷",
        "でんじは",
        "いばる"
      ]
    },
    {
      "name": "ピクシー",
      "item": "カゴのみ",
      "move": [
        "アシストパワー",
        "コスモパワー",
        "ちいさくなる",
        "ねむる"
      ]
    },
    {
      "name": "ゲンガー",
      "item": "ゲンガナイト",
      "move": [
        "たたりめ",
        "ヘドロばくだん",
        "きあいだま",
        "おにび"
      ]
    }
  ]
},
{
  "party_member_names": [
    "ミミロップ",
    "カバルドン",
    "チルタリス",
    "マニューラ",
    "ギルガルド",
    "サンダー"
  ],
  "party_member_infos": [
    {
      "name": "ミミロップ",
      "item": "ミミロップナイト",
      "move": [
        "とびひざげり",
        "おんがえし",
        "ねこだまし",
        "みがわり"
      ]
    },
    {
      "name": "カバルドン",
      "item": "ゴツゴツメット",
      "move": [
        "じしん",
        "ストーンエッジ",
        "なまける",
        "ステルスロック"
      ]
    },
    {
      "name": "チルタリス",
      "item": "チルタリスナイト",
      "move": [
        "おんがえし",
        "じしん",
        "りゅうのまい",
        "みがわり"
      ]
    },
    {
      "name": "マニューラ",
      "item": "いのちのたま",
      "move": [
        "つららおとす",
        "はたきおとす",
        "けたぐり",
        "ねこだまし"
      ]
    },
    {
      "name": "ギルガルド",
      "item": "たべのこし",
      "move": [
        "シャドーボール",
        "キングシールド",
        "どくどく",
        "みがわり"
      ]
    },
    {
      "name": "サンダー",
      "item": "オボンのみ",
      "move": [
        "ボルトチェンジ",
        "ねっぷう",
        "でんじは",
        "はねやすめ"
      ]
    }
  ]
},
{
  "party_member_names": [
    "ガブリアス",
    "ボーマンダ",
    "ウルガモス",
    "ゲンガー",
    "キノガッサ",
    "スイクン"
  ],
  "party_member_infos": [
    {
      "name": "ガブリアス",
      "item": "きあいのタスキ",
      "move": [
        "げきりん",
        "じしん",
        "がんせきふうじ",
        "つるぎのまい"
      ]
    },
    {
      "name": "ボーマンダ",
      "item": "ボーマンダナイト",
      "move": [
        "すてみタックル",
        "じしん",
        "からげんき",
        "りゅうのまい"
      ]
    },
    {
      "name": "ウルガモス",
      "item": "ラムのみ",
      "move": [
        "むしのさざめき",
        "だいもんじ",
        "めざめるパワー氷",
        ""
      ]
    },
    {
      "name": "ゲンガー",
      "item": "ゲンガナイト",
      "move": [
        "シャドーボール",
        "きあいだま",
        "ちょうはつ",
        "みちづれ"
      ]
    },
    {
      "name": "キノガッサ",
      "item": "どくどくだま",
      "move": [
        "きあいパンチ",
        "がんせきふうじ",
        "キノコのほうし",
        "みがわり"
      ]
    },
    {
      "name": "スイクン",
      "item": "ゴツゴツメット",
      "move": [
        "ねっとう",
        "れいとうビーム",
        "ミラーコート",
        "ほえる"
      ]
    }
  ]
},
{
  "party_member_names": [
    "ガルーラ",
    "サーナイト",
    "化身ボルトロス",
    "霊獣ランドロス",
    "ナットレイ",
    "マリルリ"
  ],
  "party_member_infos": [
    {
      "name": "ガルーラ",
      "item": "ガルーラナイト",
      "move": [
        "みがわり",
        "グロウパンチ",
        "じしん",
        "いわなだれ"
      ]
    },
    {
      "name": "サーナイト",
      "item": "オボンのみ",
      "move": [
        "でんじは",
        "おにび",
        "サイコキネシス",
        "ちょうはつ"
      ]
    },
    {
      "name": "化身ボルトロス",
      "item": "きあいのタスキ",
      "move": [
        "１０まんボルト",
        "めざめるパワー氷",
        "やきつくす",
        "でんじは"
      ]
    },
    {
      "name": "霊獣ランドロス",
      "item": "ゴツゴツメット",
      "move": [
        "じしん",
        "がんせき",
        "とんぼがえり",
        "ステルスロック"
      ]
    },
    {
      "name": "ナットレイ",
      "item": "たべのこし",
      "move": [
        "アイアンヘッド",
        "でんじは",
        "やどりぎのタネ",
        "みがわり"
      ]
    },
    {
      "name": "マリルリ",
      "item": "ラムのみ",
      "move": [
        "たきのぼり",
        "じゃれつく",
        "はたきおとす",
        "アクアジェット"
      ]
    }
  ]
},
{
  "party_member_names": [
    "クレッフィ",
    "ペラップ",
    "グライオン",
    "ハピナス",
    "ゲンガー",
    "クレセリア"
  ],
  "party_member_infos": [
    {
      "name": "クレッフィ",
      "item": "たべのこし",
      "move": [
        "いばる",
        "みがわり",
        "でんじは",
        "イカサマ"
      ]
    },
    {
      "name": "ペラップ",
      "item": "きあいのタスキ",
      "move": [
        "おしゃべり",
        "ばくおんぱ",
        "アンコール",
        "うたう"
      ]
    },
    {
      "name": "グライオン",
      "item": "どくどくだま",
      "move": [
        "まもる",
        "みがわり",
        "ハサミギロチン",
        "じしん"
      ]
    },
    {
      "name": "ハピナス",
      "item": "きれいなぬけがら",
      "move": [
        "でんじは",
        "シャドーボール",
        "たまごうみ",
        "ちきゅうなげ"
      ]
    },
    {
      "name": "ゲンガー",
      "item": "ゲンガナイト",
      "move": [
        "シャドーボール",
        "ヘドロばくだん",
        "みちづれ",
        "おにび"
      ]
    },
    {
      "name": "クレセリア",
      "item": "ゴツゴツメット",
      "move": [
        "サイコキネシス",
        "れいとうビーム",
        "つきのひかり",
        "どくどく"
      ]
    }
  ]
},
{
  "party_member_names": [
    "ラグラージ",
    "バシャーモ",
    "サザンドラ",
    "メタグロス",
    "化身ボルトロス",
    "ニンフィア"
  ],
  "party_member_infos": [
    {
      "name": "ラグラージ",
      "item": "ラグラージナイト",
      "move": [
        "じしん",
        "たきのぼり",
        "れいとうパンチ",
        "けたぐり"
      ]
    },
    {
      "name": "バシャーモ",
      "item": "きあいのタスキ",
      "move": [
        "ストーンエッジ",
        "つるぎのまい",
        "まもる",
        "バトンタッチ"
      ]
    },
    {
      "name": "サザンドラ",
      "item": "こだわりスカーフ",
      "move": [
        "りゅうせいぐん",
        "あくのはどう",
        "きあいだま",
        "だいもんじ"
      ]
    },
    {
      "name": "メタグロス",
      "item": "メタグロスナイト",
      "move": [
        "コメットパンチ",
        "しねんのずつき",
        "じしん",
        "れいとうパンチ"
      ]
    },
    {
      "name": "化身ボルトロス",
      "item": "オボンのみ",
      "move": [
        "ボルトチェンジ",
        "めざめるパワー氷",
        "でんじは",
        "ちょうはつ"
      ]
    },
    {
      "name": "ニンフィア",
      "item": "ラムのみ",
      "move": [
        "ハイパーボイス",
        "シャドーボール",
        "でんこうせっか",
        "あくび"
      ]
    }
  ]
},
{
  "party_member_names": [
    "バシャーモ",
    "サンダー",
    "ナットレイ",
    "ボーマンダ",
    "バンギラス",
    "ガマゲロゲ"
  ],
  "party_member_infos": [
    {
      "name": "バシャーモ",
      "item": "いのちのたま",
      "move": [
        "とびひざげり",
        "だいもんじ",
        "めざめるパワー氷",
        "まもる"
      ]
    },
    {
      "name": "サンダー",
      "item": "ゴツゴツメット",
      "move": [
        "１０まんボルト",
        "ねっぷう",
        "めざめるパワー氷",
        "はねやすめ"
      ]
    },
    {
      "name": "ナットレイ",
      "item": "たべのこし",
      "move": [
        "アイアンヘッド",
        "やどりぎのタネ",
        "ステルスロック",
        "まもる"
      ]
    },
    {
      "name": "ボーマンダ",
      "item": "ボーマンダナイト",
      "move": [
        "すてみタックル",
        "りゅうせいぐん",
        "じしん",
        "どくどく"
      ]
    },
    {
      "name": "バンギラス",
      "item": "きあいのタスキ",
      "move": [
        "いわなだれ",
        "おいうち",
        "れいとうビーム",
        "だいもんじ"
      ]
    },
    {
      "name": "ガマゲロゲ",
      "item": "ラムのみ",
      "move": [
        "ハイドロポンプ",
        "だいちのちから",
        "くさむすび",
        "みがわり"
      ]
    }
  ]
},
{
  "party_member_names": [
    "ガルーラ",
    "霊獣ランドロス",
    "キノガッサ",
    "クレセリア",
    "ヒードラン",
    "サーナイト"
  ],
  "party_member_infos": [
    {
      "name": "ガルーラ",
      "item": "ガルーラナイト",
      "move": [
        "ねこだまし",
        "すてみタックル",
        "れいとうパンチ",
        "じしん"
      ]
    },
    {
      "name": "霊獣ランドロス",
      "item": "こだわりスカーフ",
      "move": [
        "じしん",
        "ストーンエッジ",
        "はたきおとす",
        "とんぼがえり"
      ]
    },
    {
      "name": "キノガッサ",
      "item": "きあいのタスキ",
      "move": [
        "キノコのほうし",
        "タネマシンガン",
        "がんせきふうじ",
        "マッハパンチ"
      ]
    },
    {
      "name": "クレセリア",
      "item": "ゴツゴツメット",
      "move": [
        "スキルスワップ",
        "サイコキネシス",
        "でんじは",
        "つきのひかり"
      ]
    },
    {
      "name": "ヒードラン",
      "item": "たべのこし",
      "move": [
        "マグマストーム",
        "だいちのちから",
        "どくどく",
        "まもる"
      ]
    },
    {
      "name": "サーナイト",
      "item": "サーナイトナイト",
      "move": [
        "ハイパーボイス",
        "サイコショック",
        "めざめるパワー炎",
        "ちょうはつ"
      ]
    }
  ]
},
{
  "party_member_names": [
    "チルタリス",
    "グライオン",
    "ポリゴン２",
    "ヤドラン",
    "ハピナス",
    "ナットレイ"
  ],
  "party_member_infos": [
    {
      "name": "チルタリス",
      "item": "チルタリスナイト",
      "move": [
        "ハイパーボイス",
        "だいもんじ",
        "コットンガード",
        "はねやすめ"
      ]
    },
    {
      "name": "グライオン",
      "item": "どくどくだま",
      "move": [
        "ハサミギロチン",
        "じしん",
        "みがわり",
        "まもる"
      ]
    },
    {
      "name": "ポリゴン２",
      "item": "しんかのきせき",
      "move": [
        "おんがえし",
        "れいとうビーム",
        "でんじは",
        "じこさいせい"
      ]
    },
    {
      "name": "ヤドラン",
      "item": "ヤドランナイト",
      "move": [
        "ねっとう",
        "サイコキネシス",
        "れいとうビーム",
        "なまける"
      ]
    },
    {
      "name": "ハピナス",
      "item": "きれいなぬけがら",
      "move": [
        "ちきゅうなげ",
        "シャドーボール",
        "でんじは",
        "たまごうみ"
      ]
    },
    {
      "name": "ナットレイ",
      "item": "たべのこし",
      "move": [
        "パワーウィップ",
        "ジャイロボール",
        "やどりぎのタネ",
        "ステルスロック"
      ]
    }
  ]
},
{
  "party_member_names": [
    "ラティオス",
    "ラティアス",
    "バシャーモ",
    "サンダー",
    "ハッサム",
    "ガルーラ"
  ],
  "party_member_infos": [
    {
      "name": "ラティオス",
      "item": "ひかりのねんど",
      "move": [
        "リフレクター",
        "ひかりのかべ",
        "しんぴのまもり",
        "おきみやげ"
      ]
    },
    {
      "name": "ラティアス",
      "item": "ラティアスナイト",
      "move": [
        "アシストパワー",
        "めいそう",
        "みがわり",
        "じこさいせい"
      ]
    },
    {
      "name": "バシャーモ",
      "item": "じゃくてんほけん",
      "move": [
        "フレアドライブ",
        "ビルドアップ",
        "みがわり",
        "バトンタッチ"
      ]
    },
    {
      "name": "サンダー",
      "item": "オボンのみ",
      "move": [
        "ボルトチェンジ",
        "めざめるパワー氷",
        "どくどく",
        "はねやすめ"
      ]
    },
    {
      "name": "ハッサム",
      "item": "ゴツゴツメット",
      "move": [
        "バレットパンチ",
        "とんぼがえり",
        "はたきおとす",
        "はねやすめ"
      ]
    },
    {
      "name": "ガルーラ",
      "item": "ガルーラナイト",
      "move": [
        "おんがえし",
        "みがわり",
        "じしん",
        "いわなだれ"
      ]
    }
  ]
},
{
  "party_member_names": [
    "クチート",
    "クレセリア",
    "カバルドン",
    "キノガッサ",
    "ウルガモス",
    "ボーマンダ"
  ],
  "party_member_infos": [
    {
      "name": "クチート",
      "item": "クチートナイト",
      "move": [
        "ふいうち",
        "じゃれつく",
        "はたきおとす",
        "つるぎのまい"
      ]
    },
    {
      "name": "クレセリア",
      "item": "ゴツゴツメット",
      "move": [
        "サイコキネシス",
        "れいとうビーム",
        "トリックルーム",
        "みかづきのまい"
      ]
    },
    {
      "name": "カバルドン",
      "item": "オボンのみ",
      "move": [
        "じしん",
        "がんせきふうじ",
        "ステルスロック",
        "あくび"
      ]
    },
    {
      "name": "キノガッサ",
      "item": "きあいのタスキ",
      "move": [
        "マッハパンチ",
        "タネマシンガン",
        "がんせきふうじ",
        "キノコのほうし"
      ]
    },
    {
      "name": "ウルガモス",
      "item": "ラムのみ",
      "move": [
        "だいもんじ",
        "むしのさざめき",
        "ギガドレイン",
        "ちょうのまい"
      ]
    },
    {
      "name": "ボーマンダ",
      "item": "ボーマンダナイト",
      "move": [
        "すてみタックル",
        "げきりん",
        "じしん",
        "りゅうのまい"
      ]
    }
  ]
},
{
  "party_member_names": [
    "ラティアス",
    "化身ランドロス",
    "ポリゴン２",
    "ヒードラン",
    "ギャラドス",
    "キノガッサ"
  ],
  "party_member_infos": [
    {
      "name": "ラティアス",
      "item": "ラティアスナイト",
      "move": [
        "りゅうせいぐん",
        "サイコショック",
        "めいそう",
        "はねやすめ"
      ]
    },
    {
      "name": "化身ランドロス",
      "item": "こだわりスカーフ",
      "move": [
        "じしん",
        "いわなだれ",
        "とんぼがえり",
        "ばかぢから"
      ]
    },
    {
      "name": "ポリゴン２",
      "item": "しんかのきせき",
      "move": [
        "トライアタック",
        "シャドーボール",
        "れいとうビーム",
        "じこさいせい"
      ]
    },
    {
      "name": "ヒードラン",
      "item": "ふうせん",
      "move": [
        "オーバーヒート",
        "だいちのちから",
        "おにび",
        "りゅうのはどう"
      ]
    },
    {
      "name": "ギャラドス",
      "item": "ギャラドスナイト",
      "move": [
        "かみくだく",
        "りゅうのまい",
        "こおりのキバ",
        "みがわり"
      ]
    },
    {
      "name": "キノガッサ",
      "item": "きあいのタスキ",
      "move": [
        "キノコのほうし",
        "タネマシンガン",
        "マッハパンチ",
        "がんせきふうじ"
      ]
    }
  ]
},
{
  "party_member_names": [
    "ガルーラ",
    "ゲンガー",
    "クレセリア",
    "ヒードラン",
    "クレッフィ",
    "ボーマンダ"
  ],
  "party_member_infos": [
    {
      "name": "ガルーラ",
      "item": "ガルーラナイト",
      "move": [
        "ねこだまし",
        "すてみタックル",
        "グロウパンチ",
        "ふいうち"
      ]
    },
    {
      "name": "ゲンガー",
      "item": "いのちのたま",
      "move": [
        "シャドーボール",
        "きあいだま",
        "みがわり",
        "みちづれ"
      ]
    },
    {
      "name": "クレセリア",
      "item": "ゴツゴツメット",
      "move": [
        "サイコキネシス",
        "どくどく",
        "つきのひかり",
        "みかづきのまい"
      ]
    },
    {
      "name": "ヒードラン",
      "item": "こだわりメガネ",
      "move": [
        "かえんほうしゃ",
        "ラスターカノン",
        "オーバーヒート",
        "あくのはどう"
      ]
    },
    {
      "name": "クレッフィ",
      "item": "たべのこし",
      "move": [
        "でんじは",
        "いばる",
        "みがわり",
        "イカサマ"
      ]
    },
    {
      "name": "ボーマンダ",
      "item": "ボーマンダナイト",
      "move": [
        "ハイパーボイス",
        "はかいこうせん",
        "だいもんじ",
        "りゅうせいぐん"
      ]
    }
  ]
},
{
  "party_member_names": [
    "ラティオス",
    "バシャーモ",
    "ボーマンダ",
    "ウルガモス",
    "化身ボルトロス",
    "ガルーラ"
  ],
  "party_member_infos": [
    {
      "name": "ラティオス",
      "item": "ひかりのねんど",
      "move": [
        "サイコキネシス",
        "リフレクター",
        "ひかりのかべ",
        "おきみやげ"
      ]
    },
    {
      "name": "バシャーモ",
      "item": "オボンのみ",
      "move": [
        "かわらわり",
        "ビルドアップ",
        "みがわり",
        "バトンタッチ"
      ]
    },
    {
      "name": "ボーマンダ",
      "item": "ボーマンダナイト",
      "move": [
        "からげんき",
        "やつあたり",
        "じしん",
        "りゅうのまい"
      ]
    },
    {
      "name": "ウルガモス",
      "item": "ラムのみ",
      "move": [
        "かえんほうしゃ",
        "ギガドレイン",
        "むしのさざめき",
        "ちょうのまい"
      ]
    },
    {
      "name": "化身ボルトロス",
      "item": "きあいのタスキ",
      "move": [
        "１０まんボルト",
        "めざめるパワー氷",
        "ちょうはつ",
        "でんじは"
      ]
    },
    {
      "name": "ガルーラ",
      "item": "ガルーラナイト",
      "move": [
        "やつあたり",
        "じしん",
        "れいとうビーム",
        "シャドーボール"
      ]
    }
  ]
},
{
  "party_member_names": [
    "アグノム",
    "ボーマンダ",
    "キリキザン",
    "ウォッシュロトム",
    "キノガッサ",
    "ギルガルド"
  ],
  "party_member_infos": [
    {
      "name": "アグノム",
      "item": "たつじんのおび",
      "move": [
        "サイコキネシス",
        "だいもんじ",
        "くさむすび",
        "めざめるパワー氷"
      ]
    },
    {
      "name": "ボーマンダ",
      "item": "ボーマンダナイト",
      "move": [
        "ハイパーボイス",
        "りゅうせいぐん",
        "だいもんじ",
        "どくどく"
      ]
    },
    {
      "name": "キリキザン",
      "item": "いのちのたま",
      "move": [
        "はたきおとす",
        "アイアンヘッド",
        "ふいうち",
        "つるぎのまい"
      ]
    },
    {
      "name": "ウォッシュロトム",
      "item": "オボンのみ",
      "move": [
        "ハイドロポンプ",
        "１０まんボルト",
        "ボルトチェンジ",
        "おにび"
      ]
    },
    {
      "name": "キノガッサ",
      "item": "きあいのタスキ",
      "move": [
        "タネマシンガン",
        "マッハパンチ",
        "がんせきふうじ",
        "キノコのほうし"
      ]
    },
    {
      "name": "ギルガルド",
      "item": "じゃくてんほけん",
      "move": [
        "シャドーボール",
        "ラスターかのん",
        "かげうち",
        "キングシールド"
      ]
    }
  ]
},
{
  "party_member_names": [
    "霊獣ランドロス",
    "ボーマンダ",
    "シャワーズ",
    "レントラー",
    "モロバレル",
    "ガルーラ"
  ],
  "party_member_infos": [
    {
      "name": "霊獣ランドロス",
      "item": "とつげきチョッキ",
      "move": [
        "じしん",
        "がんせきふうじ",
        "はたきおとす",
        "とんぼがえり"
      ]
    },
    {
      "name": "シャワーズ",
      "item": "たべのこし",
      "move": [
        "ねっとう",
        "みがわり",
        "あくび",
        "バトンタッチ"
      ]
    },
    {
      "name": "レントラー",
      "item": "オボンのみ",
      "move": [
        "ボルトチェンジ",
        "めざめるパワー氷",
        "ばかぢから",
        "でんじは"
      ]
    },
    {
      "name": "モロバレル",
      "item": "くろいヘドロ",
      "move": [
        "ギガドレイン",
        "イカサマ",
        "ヘドロばくだん",
        "キノコのほうし"
      ]
    },
    {
      "name": "ガルーラ",
      "item": "ガルーラナイト",
      "move": [
        "ねこだまし",
        "すてみタックル",
        "グロウパンチ",
        "ふいうち"
      ]
    },
    {
      "name": "ボーマンダ",
      "item": "ボーマンダナイト",
      "move": [
        "ハイパーボイス",
        "りゅうせいぐん",
        "だいもんじ",
        "はかいこうせん"
      ]
    }
  ]
},
{
  "party_member_names": [
    "バクーダ",
    "トゲキッス",
    "ヤドラン",
    "ナットレイ",
    "サザンドラ",
    "ギルガルド"
  ],
  "party_member_infos": [
    {
      "name": "バクーダ",
      "item": "バクーダナイト",
      "move": [
        "だいもんじ",
        "だいちのちから",
        "めざめるパワー氷",
        "いわなだれ"
      ]
    },
    {
      "name": "トゲキッス",
      "item": "こだわりスカーフ",
      "move": [
        "エアスラッシュ",
        "マジカルシャイン",
        "でんじは",
        "トリック"
      ]
    },
    {
      "name": "ヤドラン",
      "item": "ゴツゴツメット",
      "move": [
        "ねっとう",
        "サイコキネシス",
        "でんじは",
        "なまける"
      ]
    },
    {
      "name": "ナットレイ",
      "item": "たべのこし",
      "move": [
        "パワーウィップ",
        "アイアンヘッド",
        "でんじは",
        "やどりぎのタネ"
      ]
    },
    {
      "name": "サザンドラ",
      "item": "こだわりメガネ",
      "move": [
        "りゅうせいぐん",
        "あくのはどう",
        "ラスターカノン",
        "かえんほうしゃ"
      ]
    },
    {
      "name": "ギルガルド",
      "item": "ラムのみ",
      "move": [
        "シャドークロー",
        "かげうち",
        "せいなるつるぎ",
        "つるぎのまい"
      ]
    }
  ]
},
{
  "party_member_names": [
    "バシャーモ",
    "ドリュウズ",
    "ウォッシュロトム",
    "エルフーン",
    "クレセリア",
    "ゲンガー"
  ],
  "party_member_infos": [
    {
      "name": "バシャーモ",
      "item": "バシャーモナイト",
      "move": [
        "とびひざげり",
        "フレアドライブ",
        "まもる",
        "つるぎのまい"
      ]
    },
    {
      "name": "ドリュウズ",
      "item": "こだわりスカーフ",
      "move": [
        "じしん",
        "アイアンヘッド",
        "いわなだれ",
        "つのドリル"
      ]
    },
    {
      "name": "ウォッシュロトム",
      "item": "オボンのみ",
      "move": [
        "１０まんボルト",
        "ハイドロポンプ",
        "おにび",
        "ボルトチェンジ"
      ]
    },
    {
      "name": "エルフーン",
      "item": "たべのこし",
      "move": [
        "ムーンフォース",
        "やどりぎのタネ",
        "みがわり",
        "アンコール"
      ]
    },
    {
      "name": "クレセリア",
      "item": "ゴツゴツメット",
      "move": [
        "サイコキネシス",
        "どくどく",
        "でんじは",
        "つきのひかり"
      ]
    },
    {
      "name": "ゲンガー",
      "item": "ゲンガナイト",
      "move": [
        "シャドーボール",
        "きあいだま",
        "おにび",
        "みちづれ"
      ]
    }
  ]
},
{
  "party_member_names": [
    "ガルーラ",
    "バシャーモ",
    "サーナイト",
    "ウォッシュロトム",
    "霊獣ランドロス",
    "ギルガルド"
  ],
  "party_member_infos": [
    {
      "name": "ガルーラ",
      "item": "ガルーラナイト",
      "move": [
        "すてみタックル",
        "ねこだまし",
        "グロウパンチ",
        "ふいうち"
      ]
    },
    {
      "name": "バシャーモ",
      "item": "バシャーモナイト",
      "move": [
        "オーバーヒート",
        "とびひざげり",
        "めざめるパワー氷",
        "まもる"
      ]
    },
    {
      "name": "サーナイト",
      "item": "サーナイトナイト",
      "move": [
        "サイコショック",
        "ハイパーボイス",
        "めざめるパワー地",
        "ちょうはつ"
      ]
    },
    {
      "name": "ウォッシュロトム",
      "item": "オボンのみ",
      "move": [
        "１０まんボルト",
        "ボルトチェンジ",
        "ハイドロポンプ",
        "おにび"
      ]
    },
    {
      "name": "霊獣ランドロス",
      "item": "とつげきチョッキ",
      "move": [
        "じしん",
        "がんせきふうじ",
        "とんぼがえり",
        "はたきおとす"
      ]
    },
    {
      "name": "ギルガルド",
      "item": "ラムのみ",
      "move": [
        "シャドークロー",
        "かげうち",
        "キングシールド",
        "つるぎのまい"
      ]
    }
  ]
},
{
  "party_member_names": [
    "化身ボルトロス",
    "霊獣ランドロス",
    "ガルーラ",
    "ゲンガー",
    "スイクン",
    "クレセリア"
  ],
  "party_member_infos": [
    {
      "name": "化身ボルトロス",
      "item": "いのちのたま",
      "move": [
        "ボルトチェンジ",
        "くさむすび",
        "でんじは",
        "めざめるパワー氷"
      ]
    },
    {
      "name": "霊獣ランドロス",
      "item": "こだわりスカーフ",
      "move": [
        "じしん",
        "ばかぢから",
        "とんぼがえり",
        "いわなだれ"
      ]
    },
    {
      "name": "ガルーラ",
      "item": "ガルーラナイト",
      "move": [
        "すてみタックル",
        "ほのおのパンチ",
        "れいとうパンチ",
        "じしん"
      ]
    },
    {
      "name": "ゲンガー",
      "item": "きあいのタスキ",
      "move": [
        "シャドーボール",
        "ちょうはつ",
        "みちづれ",
        "ヘドロばくだん"
      ]
    },
    {
      "name": "スイクン",
      "item": "カゴのみ",
      "move": [
        "ねっとう",
        "れいとうビーム",
        "めいそう",
        "ねむる"
      ]
    },
    {
      "name": "クレセリア",
      "item": "ゴツゴツメット",
      "move": [
        "サイコキネシス",
        "れいとうビーム",
        "つきのひかり",
        "どくどく"
      ]
    }
  ]
},
{
  "party_member_names": [
    "ヤミラミ",
    "ドーブル",
    "ボーマンダ",
    "カメックス",
    "ギルガルド",
    "ポリゴン２"
  ],
  "party_member_infos": [
    {
      "name": "ヤミラミ",
      "item": "ロゼルのみ",
      "move": [
        "がんせきふうじ",
        "ちょうはつ",
        "みがわり",
        "おにび"
      ]
    },
    {
      "name": "ドーブル",
      "item": "パワフルハーブ",
      "move": [
        "ジオコントロール",
        "バトンタッチ",
        "ちょうはつ",
        "キングシールド"
      ]
    },
    {
      "name": "ボーマンダ",
      "item": "ボーマンダナイト",
      "move": [
        "ハイパーボイス",
        "だいもんじ",
        "ねむる",
        "ねごと"
      ]
    },
    {
      "name": "カメックス",
      "item": "カメックスナイト",
      "move": [
        "みずのはどう",
        "あくのはどう",
        "はどうだん",
        "れいとうビーム"
      ]
    },
    {
      "name": "ギルガルド",
      "item": "たべのこし",
      "move": [
        "アイアンヘッド",
        "どくどく",
        "みがわり",
        "キングシールド"
      ]
    },
    {
      "name": "ポリゴン２",
      "item": "しんかのきせき",
      "move": [
        "トライアタック",
        "れいとうビーム",
        "でんじは",
        "じこさいせい"
      ]
    }
  ]
},
{
  "party_member_names": [
    "サーナイト",
    "バシャーモ",
    "ガブリアス",
    "ハッサム",
    "サンダー",
    "スイクン"
  ],
  "party_member_infos": [
    {
      "name": "サーナイト",
      "item": "サーナイトナイト",
      "move": [
        "ハイパーボイス",
        "サイコショック",
        "めざめるパワー地",
        "ちょうはつ"
      ]
    },
    {
      "name": "バシャーモ",
      "item": "バシャーモナイト",
      "move": [
        "ばかぢから",
        "フレアドライブ",
        "かみなりパンチ",
        "まもる"
      ]
    },
    {
      "name": "ガブリアス",
      "item": "ラムのみ",
      "move": [
        "げきりん",
        "じしん",
        "がんせきふうじ",
        "つるぎのまい"
      ]
    },
    {
      "name": "ハッサム",
      "item": "こだわりハチマキ",
      "move": [
        "バレットパンチ",
        "はたきおとす",
        "ばかぢから",
        "とんぼがえり"
      ]
    },
    {
      "name": "サンダー",
      "item": "ゴツゴツメット",
      "move": [
        "ボルトチェンジ",
        "ねっぷう",
        "はねやすめ",
        "どくどく"
      ]
    },
    {
      "name": "スイクン",
      "item": "カゴのみ",
      "move": [
        "ねっとう",
        "ほえる",
        "めいそう",
        "ねむる"
      ]
    }
  ]
},
{
  "party_member_names": [
    "霊獣ランドロス",
    "サンダー",
    "シャワーズ",
    "バシャーモ",
    "モロバレル",
    "ガルーラ"
  ],
  "party_member_infos": [
    {
      "name": "霊獣ランドロス",
      "item": "とつげきチョッキ",
      "move": [
        "じしん",
        "がんせきふうじ",
        "はたきおとす",
        "とんぼがえり"
      ]
    },
    {
      "name": "サンダー",
      "item": "オボンのみ",
      "move": [
        "１０まんボルト",
        "めざめるパワー氷",
        "でんじは",
        "はねやすめ"
      ]
    },
    {
      "name": "バシャーモ",
      "item": "バシャーモナイト",
      "move": [
        "フレアドライブ",
        "とびひざげり",
        "かみなりパンチ",
        "まもる"
      ]
    },
    {
      "name": "シャワーズ",
      "item": "たべのこし",
      "move": [
        "ねっとう",
        "あくび",
        "みがわり",
        "バトンタッチ"
      ]
    },
    {
      "name": "モロバレル",
      "item": "くろいヘドロ",
      "move": [
        "ギガドレイン",
        "ヘドロばくだん",
        "キノコのほうし",
        "イカサマ"
      ]
    },
    {
      "name": "ガルーラ",
      "item": "ガルーラナイト",
      "move": [
        "ねこだまし",
        "すてみタックル",
        "グロウパンチ",
        "ふいうち"
      ]
    }
  ]
},
{
  "party_member_names": [
    "チルタリス",
    "バンギラス",
    "ドリュウズ",
    "ローブシン",
    "ソーナンス",
    "サマヨール"
  ],
  "party_member_infos": [
    {
      "name": "チルタリス",
      "item": "チルタリスナイト",
      "move": [
        "おんがえし",
        "じしん",
        "りゅうまい",
        "みがわり"
      ]
    },
    {
      "name": "バンギラス",
      "item": "さらさらいわ",
      "move": [
        "だいもんじ",
        "れいとうビーム",
        "ステルスロック",
        "ほえる"
      ]
    },
    {
      "name": "ドリュウズ",
      "item": "いのちのたま",
      "move": [
        "じしん",
        "アイアンヘッド",
        "いわなだれ",
        "つるぎのまい"
      ]
    },
    {
      "name": "ローブシン",
      "item": "ぼうじんゴーグル",
      "move": [
        "ドレインパンチ",
        "マッハパンチ",
        "れいとうパンチ",
        "かみなりパンチ"
      ]
    },
    {
      "name": "ソーナンス",
      "item": "オボンのみ",
      "move": [
        "ミラーコート",
        "カウンター",
        "みちづれ",
        "アンコール"
      ]
    },
    {
      "name": "サマヨール",
      "item": "しんかのきせき",
      "move": [
        "スキルスワップ",
        "おにび",
        "くろいまなざし",
        "ねむる"
      ]
    }
  ]
},
{
  "party_member_names": [
    "ウルガモス",
    "ガルーラ",
    "クレセリア",
    "霊獣ランドロス",
    "ギルガルド",
    "スイクン"
  ],
  "party_member_infos": [
    {
      "name": "ウルガモス",
      "item": "ラムのみ",
      "move": [
        "だいもんじ",
        "めざめるパワー地",
        "ギガドレイン",
        "ちょうのまい"
      ]
    },
    {
      "name": "ガルーラ",
      "item": "ガルーラナイト",
      "move": [
        "ねこだまし",
        "すてみタックル",
        "れいとうパンチ",
        "じしん"
      ]
    },
    {
      "name": "クレセリア",
      "item": "ゴツゴツメット",
      "move": [
        "サイコショック",
        "れいとうビーム",
        "つきのひかり",
        "みかづきのまい"
      ]
    },
    {
      "name": "霊獣ランドロス",
      "item": "こだわりスカーフ",
      "move": [
        "じしん",
        "いわなだれ",
        "はたきおとす",
        "とんぼがえり"
      ]
    },
    {
      "name": "ギルガルド",
      "item": "じゃくてんほけん",
      "move": [
        "シャドーボール",
        "せいなるつるぎ",
        "かげうち",
        "キングシールド"
      ]
    },
    {
      "name": "スイクン",
      "item": "カゴのみ",
      "move": [
        "ねっとう",
        "ほえる",
        "しおふき",
        "ねむる"
      ]
    }
  ]
},
{
  "party_member_names": [
    "化身ボルトロス",
    "マンムー",
    "クレッフィ",
    "ゲンガー",
    "ボーマンダ",
    "ラッキー"
  ],
  "party_member_infos": [
    {
      "name": "化身ボルトロス",
      "item": "オボンのみ",
      "move": [
        "１０まんボルト",
        "めざめるパワー氷",
        "でんじは",
        "ちょうはつ"
      ]
    },
    {
      "name": "マンムー",
      "item": "ゴツゴツメット",
      "move": [
        "じしん",
        "こおりのつぶて",
        "どくどく",
        "ステルスロック"
      ]
    },
    {
      "name": "クレッフィ",
      "item": "たべのこし",
      "move": [
        "イカサマ",
        "でんじは",
        "いばる",
        "みがわり"
      ]
    },
    {
      "name": "ゲンガー",
      "item": "ゲンガナイト",
      "move": [
        "たたりめ",
        "ヘドロばくだん",
        "みがわり",
        "おにび"
      ]
    },
    {
      "name": "ボーマンダ",
      "item": "ボーマンダナイト",
      "move": [
        "やつあたり",
        "じしん",
        "どくどく",
        "はねやすめ"
      ]
    },
    {
      "name": "ラッキー",
      "item": "しんかのきせき",
      "move": [
        "ちきゅうなげ",
        "でんじは",
        "いばる",
        "ちょうはつ"
      ]
    }
  ]
},
{
  "party_member_names": [
    "ラグラージ",
    "ボーマンダ",
    "マンムー",
    "スイクン",
    "ジャローダ",
    "バンギラス"
  ],
  "party_member_infos": [
    {
      "name": "ラグラージ",
      "item": "オボンのみ",
      "move": [
        "なみのり",
        "ステルスロック",
        "あくび",
        "ほえる"
      ]
    },
    {
      "name": "ボーマンダ",
      "item": "ボーマンダナイト",
      "move": [
        "すてみタックル",
        "からげんき",
        "じしん",
        "りゅうのまい"
      ]
    },
    {
      "name": "マンムー",
      "item": "こだわりスカーフ",
      "move": [
        "つららばり",
        "じしん",
        "いわなだれ",
        "ばかぢから"
      ]
    },
    {
      "name": "スイクン",
      "item": "ゴツゴツメット",
      "move": [
        "ねっとう",
        "めいそう",
        "ねごと",
        "ねむる"
      ]
    },
    {
      "name": "ジャローダ",
      "item": "きあいのタスキ",
      "move": [
        "リーフストーム",
        "りゅうのはどう",
        "めざめるパワー炎",
        "へびにらみ"
      ]
    },
    {
      "name": "バンギラス",
      "item": "バンギラスナイト",
      "move": [
        "ストーンエッジ",
        "けたぐり",
        "りゅうのまい",
        "みがわり"
      ]
    }
  ]
},
{
  "party_member_names": [
    "リザードン",
    "カバルドン",
    "キノガッサ",
    "ガルーラ",
    "スイクン",
    "ギルガルド"
  ],
  "party_member_infos": [
    {
      "name": "リザードン",
      "item": "リザードナイトX",
      "move": [
        "げきりん",
        "フレアドライブ",
        "ニトロチャージ",
        "つるぎのまい"
      ]
    },
    {
      "name": "カバルドン",
      "item": "ゴツゴツメット",
      "move": [
        "なまける",
        "じしん",
        "あくび",
        "こおりのキバ"
      ]
    },
    {
      "name": "スイクン",
      "item": "カゴのみ",
      "move": [
        "ねむる",
        "めいそう",
        "ねっとう",
        "れいとうビーム"
      ]
    },
    {
      "name": "ギルガルド",
      "item": "たべのこし",
      "move": [
        "キングシールド",
        "みがわり",
        "どくどく",
        "シャドーボール"
      ]
    },
    {
      "name": "キノガッサ",
      "item": "きあいのタスキ",
      "move": [
        "マッハパンチ",
        "がんせきふうじ",
        "タネマシンガン",
        "キノコのほうし"
      ]
    },
    {
      "name": "ガルーラ",
      "item": "ガルーラナイト",
      "move": [
        "すてみタックル",
        "ふいうち",
        "だいもんじ",
        "れいとうビーム"
      ]
    }
  ]
},
{
  "party_member_names": [
    "バンギラス",
    "エアームド",
    "ラッキー",
    "オーロット",
    "ヤドラン",
    "ハッサム"
  ],
  "party_member_infos": [
    {
      "name": "バンギラス",
      "item": "ラムのみ",
      "move": [
        "かみくだく",
        "いわなだれ",
        "ほえる",
        "ねむる"
      ]
    },
    {
      "name": "エアームド",
      "item": "ゴツゴツメット",
      "move": [
        "アイアンヘッド",
        "ちょうはつ",
        "はねやすめ",
        "ほえる"
      ]
    },
    {
      "name": "ラッキー",
      "item": "しんかのきせき",
      "move": [
        "ちきゅうなげ",
        "でんじは",
        "ステルスロック",
        "たまごうみ"
      ]
    },
    {
      "name": "オーロット",
      "item": "オボンのみ",
      "move": [
        "やどりぎのタネ",
        "のろい",
        "みがわり",
        "まもる"
      ]
    },
    {
      "name": "ヤドラン",
      "item": "ヤドランナイト",
      "move": [
        "ねっとう",
        "れいとうビーム",
        "だいもんじ",
        "なまける"
      ]
    },
    {
      "name": "ハッサム",
      "item": "ハッサムナイト",
      "move": [
        "バレットパンチ",
        "はたきおとす",
        "つるぎのまい",
        "はねやすめ"
      ]
    }
  ]
},
{
  "party_member_names": [
    "ライボルト",
    "霊獣ランドロス",
    "クレセリア",
    "ヒードラン",
    "キノガッサ",
    "ガルーラ"
  ],
  "party_member_infos": [
    {
      "name": "ライボルト",
      "item": "ライボルトナイト",
      "move": [
        "めざめるパワー氷",
        "１０まんボルト",
        "かえんほうしゃ",
        "ボルトチェンジ"
      ]
    },
    {
      "name": "霊獣ランドロス",
      "item": "こだわりスカーフ",
      "move": [
        "じしん",
        "とんぼがえり",
        "いわなだれ",
        "ばかぢから"
      ]
    },
    {
      "name": "クレセリア",
      "item": "ゴツゴツメット",
      "move": [
        "サイコキネシス",
        "れいとうビーム",
        "つきのひかり",
        "でんじは"
      ]
    },
    {
      "name": "ヒードラン",
      "item": "たべのこし",
      "move": [
        "マグマストーム",
        "だいちのちから",
        "どくどく",
        "まもる"
      ]
    },
    {
      "name": "キノガッサ",
      "item": "どくどくだま",
      "move": [
        "キノコのほうし",
        "みがわり",
        "タネマシンガン",
        "ビルドアップ"
      ]
    },
    {
      "name": "ガルーラ",
      "item": "ガルーラナイト",
      "move": [
        "グロウパンチ",
        "ふいうち",
        "けたぐり",
        "すてみタックル"
      ]
    }
  ]
},
{
  "party_member_names": [
    "ゲンガー",
    "サンダー",
    "ヒードラン",
    "ポリゴン２",
    "霊獣ランドロス",
    "ゲッコウガ"
  ],
  "party_member_infos": [
    {
      "name": "ゲンガー",
      "item": "ゲンガナイト",
      "move": [
        "みちづれ",
        "シャドーボール",
        "ちょうはつ",
        "ヘドロばくだん"
      ]
    },
    {
      "name": "サンダー",
      "item": "ゴツゴツメット",
      "move": [
        "１０まんボルト",
        "めざめるパワー氷",
        "どくどく",
        "はねやすめ"
      ]
    },
    {
      "name": "ヒードラン",
      "item": "たべのこし",
      "move": [
        "マグマストーム",
        "どくどく",
        "だいちのちから",
        "まもる"
      ]
    },
    {
      "name": "ポリゴン２",
      "item": "しんかのきせき",
      "move": [
        "イカサマ",
        "でんじは",
        "じこさいせい",
        "れいとうビーム"
      ]
    },
    {
      "name": "霊獣ランドロス",
      "item": "こだわりスカーフ",
      "move": [
        "じしん",
        "はたきおとす",
        "とんぼがえり",
        "ばかぢから"
      ]
    },
    {
      "name": "ゲッコウガ",
      "item": "きあいのタスキ",
      "move": [
        "あくのはどう",
        "れいとうビーム",
        "ダストシュート",
        "ハイドロポンプ"
      ]
    }
  ]
},
{
  "party_member_names": [
    "ゲンガー",
    "グライオン",
    "ポリゴン２",
    "ヤドラン",
    "ハピナス",
    "モロバレル"
  ],
  "party_member_infos": [
    {
      "name": "ゲンガー",
      "item": "ゲンガナイト",
      "move": [
        "シャドーボール",
        "ヘドロばくだん",
        "ちょうはつ",
        "みちづれ"
      ]
    },
    {
      "name": "グライオン",
      "item": "どくどくだま",
      "move": [
        "ハサミギロチン",
        "じしん",
        "みがわり",
        "まもる"
      ]
    },
    {
      "name": "ポリゴン２",
      "item": "しんかのきせき",
      "move": [
        "おんがえし",
        "れいとうビーム",
        "でんじは",
        "じこさいせい"
      ]
    },
    {
      "name": "ヤドラン",
      "item": "ヤドランナイト",
      "move": [
        "ねっとう",
        "てっぺき",
        "れいとうビーム",
        "なまける"
      ]
    },
    {
      "name": "ハピナス",
      "item": "きれいなぬけがら",
      "move": [
        "ちきゅうなげ",
        "シャドーボール",
        "でんじは",
        "たまごうみ"
      ]
    },
    {
      "name": "モロバレル",
      "item": "くろいヘドロ",
      "move": [
        "ギガドレイン",
        "クリアスモッグ",
        "イカサマ",
        "こうごうせい"
      ]
    }
  ]
}]