{
  "simple_party": [
    "",
    "",
    "",
    "",
    "",
    ""
  ],
  "detailed_party": [
    {
      "name": "",
      "item": "",
      "move": [
        "",
        "",
        "",
        ""
      ]
    },
    {
      "name": "",
      "item": "",
      "move": [
        "",
        "",
        "",
        ""
      ]
    },
    {
      "name": "",
      "item": "",
      "move": [
        "",
        "",
        "",
        ""
      ]
    },
    {
      "name": "",
      "item": "",
      "move": [
        "",
        "",
        "",
        ""
      ]
    },
    {
      "name": "",
      "item": "",
      "move": [
        "",
        "",
        "",
        ""
      ]
    },
    {
      "name": "",
      "item": "",
      "move": [
        "",
        "",
        "",
        ""
      ]
    }
  ]
}